{"lastUsed":1594712325116,"path":"C:\/My_Study\/Web_Study","projectCount":2,"recentFiles":[{"path":"\/2020_0714_SessionTracking\/src\/action","parentWorkspace":"C:\/My_Study\/Web_Study","name":"TestSessionAction.java","lastModified":1594712361123,"locationURI":"file:\/C:\/My_Study\/Web_Study\/2020_0714_SessionTracking\/src\/action\/TestSessionAction.java"},{"path":"\/Servers\/Tomcat v8.5 Server at localhost-config","parentWorkspace":"C:\/My_Study\/Web_Study","name":"logging.properties","lastModified":1594106634217,"locationURI":"file:\/C:\/My_Study\/Web_Study\/Servers\/Tomcat%20v8.5%20Server%20at%20localhost-config\/logging.properties"},{"path":"\/2020_0714_SessionTracking\/WebContent\/session_test","parentWorkspace":"C:\/My_Study\/Web_Study","name":"a.jsp","lastModified":1594711799696,"locationURI":"file:\/C:\/My_Study\/Web_Study\/2020_0714_SessionTracking\/WebContent\/session_test\/a.jsp"},{"path":"\/Servers\/Tomcat v8.5 Server at localhost-config","parentWorkspace":"C:\/My_Study\/Web_Study","name":"catalina.properties","lastModified":1594106770334,"locationURI":"file:\/C:\/My_Study\/Web_Study\/Servers\/Tomcat%20v8.5%20Server%20at%20localhost-config\/catalina.properties"}]}